iron_sql/__init__.py
iron_sql/generator.py
iron_sql/runtime.py
iron_sql/sqlc.py
iron_sql-0.2.5.dist-info/licenses/LICENSE
iron_sql-0.2.5.dist-info/WHEEL
iron_sql-0.2.5.dist-info/METADATA
iron_sql-0.2.5.dist-info/RECORD
