Metadata-Version: 2.4
Name: iron-sql
Version: 0.2.5
Summary: iron_sql generates typed async PostgreSQL clients and runtime helpers from schemas and SQL queries
Keywords: postgresql,sql,sqlc,psycopg,codegen,async
Author: Ilia Ablamonov
Author-email: Ilia Ablamonov <ilia@flamefork.ru>
License-Expression: MIT
License-File: LICENSE
Classifier: Development Status :: 3 - Alpha
Classifier: Intended Audience :: Developers
Classifier: Topic :: Software Development :: Libraries
Classifier: Programming Language :: Python :: 3
Classifier: Programming Language :: Python :: 3.13
Requires-Dist: inflection>=0.5.1
Requires-Dist: psycopg>=3.3.2
Requires-Dist: psycopg-pool>=3.3.0
Requires-Dist: pydantic>=2.12.4
Requires-Python: >=3.13
Project-URL: Homepage, https://github.com/Flamefork/iron_sql
Project-URL: Repository, https://github.com/Flamefork/iron_sql.git
Project-URL: Issues, https://github.com/Flamefork/iron_sql/issues
